Metadata-Version: 2.1
Name: collect-framework-test
Version: 1.1.1
Summary: Simple collect framework
Home-page: UNKNOWN
Author: Drakosha295
License: UNKNOWN
Platform: UNKNOWN
License-File: LICENSE.txt
